incremental_module_loader.py
incremental_module_loader-1.0.0.dist-info/LICENSE
incremental_module_loader-1.0.0.dist-info/METADATA
incremental_module_loader-1.0.0.dist-info/WHEEL
incremental_module_loader-1.0.0.dist-info/top_level.txt
incremental_module_loader-1.0.0.dist-info/RECORD
