Metadata-Version: 2.1
Name: incremental-module-loader
Version: 1.0.0
Summary: Micro-framework to allow incremental dependencies injection in inter-related modules.
Home-page: https://gitlab.com/tackv/incremental-module-loader
Author: William Laroche
Author-email: william.laroche@tackv.ca
Maintainer: William Laroche
Maintainer-email: william.laroche@tackv.ca
License: MIT
Platform: UNKNOWN
Classifier: Development Status :: 5 - Production/Stable
Classifier: Intended Audience :: Developers
Classifier: Topic :: Software Development
Classifier: Topic :: Software Development :: Testing
Classifier: Topic :: Utilities
Classifier: License :: OSI Approved :: MIT License
Classifier: Programming Language :: Python :: 3.6
